.gitignore
.pre-commit-config.yaml
.pylintrc
.readthedocs.yml
CODE_OF_CONDUCT.md
LICENSE
README.rst
README.rst.license
displayio_flipinput.py
pyproject.toml
requirements.txt
setup.py
.github/workflows/build.yml
.github/workflows/failure-help-text.yml
.github/workflows/release.yml
LICENSES/CC-BY-4.0.txt
LICENSES/MIT.txt
LICENSES/OFL-1.1.txt
LICENSES/Unlicense.txt
circuitpython_displayio_flipinput.egg-info/PKG-INFO
circuitpython_displayio_flipinput.egg-info/SOURCES.txt
circuitpython_displayio_flipinput.egg-info/dependency_links.txt
circuitpython_displayio_flipinput.egg-info/requires.txt
circuitpython_displayio_flipinput.egg-info/top_level.txt
docs/api.rst
docs/api.rst.license
docs/conf.py
docs/examples.rst
docs/examples.rst.license
docs/index.rst
docs/index.rst.license
docs/_static/favicon.ico
docs/_static/favicon.ico.license
examples/displayio_flipinput_simpletest.py
examples/fonts/DSEG14Classic-Regular-64-ModS.pcf
examples/fonts/DSEG14Classic-Regular-64-ModS.pcf.license