Metadata-Version: 2.1
Name: circuitpython-displayio-flipinput
Version: 0.1.0
Summary: A flip style input selector. The value changes based on touch inputs
Home-page: https://github.com/circuitpython/CircuitPython_Org_DisplayIO_FlipInput.git
Author: Kevin Matocha
Author-email: 
License: MIT
Keywords: adafruit blinka circuitpython micropython displayio_flipinput  two halves of the indicator with optional arrows added.displayio widget graphics
Platform: UNKNOWN
Classifier: Development Status :: 3 - Alpha
Classifier: Intended Audience :: Developers
Classifier: Topic :: Software Development :: Libraries
Classifier: Topic :: System :: Hardware
Classifier: License :: OSI Approved :: MIT License
Classifier: Programming Language :: Python :: 3
Classifier: Programming Language :: Python :: 3.4
Classifier: Programming Language :: Python :: 3.5
